drf_model_serializer/__init__.py
drf_model_serializer/serializers.py
drf_model_serializer-0.0.2.dist-info/LICENSE
drf_model_serializer-0.0.2.dist-info/METADATA
drf_model_serializer-0.0.2.dist-info/WHEEL
drf_model_serializer-0.0.2.dist-info/top_level.txt
drf_model_serializer-0.0.2.dist-info/RECORD
