Metadata-Version: 2.1
Name: drf-model-serializer
Version: 0.0.2
Summary: A simple library that enhance 'ModelSerializer' class so that it performs object-level validation for free.
Home-page: https://github.com/senseobservationsystems/drf-model-serializer
Author: Panji Y. Wiwaha
Author-email: panjiyudasetya@gmail.com
License: UNKNOWN
Keywords: django,drf,serializer
Platform: UNKNOWN
Classifier: Environment :: Web Environment
Classifier: Framework :: Django
Classifier: License :: OSI Approved :: MIT License
Classifier: Operating System :: OS Independent
Classifier: Programming Language :: Python
Classifier: Programming Language :: Python :: 2.7
Classifier: Programming Language :: Python :: 3
Classifier: Programming Language :: Python :: 3.3
Classifier: Topic :: Software Development :: Libraries :: Python Modules
Classifier: Topic :: Utilities
Classifier: Topic :: Software Development :: Libraries :: Application Frameworks
Classifier: Topic :: Software Development :: Libraries :: Python Modules
Requires-Dist: django
Requires-Dist: djangorestframework
